FortiJson/__init__.py
FortiJson/rpcrequest.py
FortiJson-1.0.dist-info/LICENSE.txt
FortiJson-1.0.dist-info/METADATA
FortiJson-1.0.dist-info/WHEEL
FortiJson-1.0.dist-info/top_level.txt
FortiJson-1.0.dist-info/RECORD
